mpesa/LipaNaMpesaOnline.py
mpesa/__init__.py
mpesa/admin.py
mpesa/apps.py
mpesa/models.py
mpesa/settings.py
mpesa/tests.py
mpesa/urls.py
mpesa/views.py
mpesa/migrations/0001_initial.py
mpesa/migrations/0002_wallet.py
mpesa/migrations/0003_paymenttransaction_order_id.py
mpesa/migrations/0004_auto_20200809_1604.py
mpesa/migrations/0005_auto_20200822_1645.py
mpesa/migrations/0006_auto_20220108_1033.py
mpesa/migrations/0007_auto_20220121_0911.py
mpesa/migrations/__init__.py
django_mpesa-2.0.14.dist-info/LICENSE
django_mpesa-2.0.14.dist-info/METADATA
django_mpesa-2.0.14.dist-info/WHEEL
django_mpesa-2.0.14.dist-info/top_level.txt
django_mpesa-2.0.14.dist-info/RECORD
