Metadata-Version: 2.1
Name: django-mpesa
Version: 2.0.14
Summary: A python library that interfaces safaricoms mpesa apis
Home-page: https://www.vorane.com/
Author: Paul Ekirapa
Author-email: ekirapapaul@gmail.com
License: MIT
Platform: UNKNOWN
Classifier: Environment :: Web Environment
Classifier: Framework :: Django
Classifier: Framework :: Django :: 2.2
Classifier: Intended Audience :: Developers
Classifier: License :: OSI Approved :: BSD License
Classifier: Operating System :: OS Independent
Classifier: Programming Language :: Python
Classifier: Programming Language :: Python :: 3.6
Classifier: Programming Language :: Python :: 3.7
Classifier: Programming Language :: Python :: 3.8
Classifier: Programming Language :: Python :: 3.9
Provides-Extra: test
Provides-Extra: lint
Provides-Extra: dev
License-File: LICENSE
